ryo/__init__.py
ryo/aws.py
ryo/cli.py
ryo/core.py
ryo/github.py
ryo/runner.py
ryo/utils.py
ryo-0.1.9.dist-info/licenses/LICENSE
tests/__init__.py
tests/test_core.py
tests/test_github.py
tests/test_runner.py
tests/test_utils.py
ryo-0.1.9.dist-info/METADATA
ryo-0.1.9.dist-info/WHEEL
ryo-0.1.9.dist-info/entry_points.txt
ryo-0.1.9.dist-info/top_level.txt
ryo-0.1.9.dist-info/RECORD
